extproxy/__init__.py
extproxy/compat.py
extproxy/extra.py
extproxy/https.py
extproxy/socket_inet_p.py
extproxy/socks.py
extproxy/ssl_wrap_socket.py
extproxy/util.py
ExtProxy-1.0.3.dist-info/LICENSE
ExtProxy-1.0.3.dist-info/METADATA
ExtProxy-1.0.3.dist-info/WHEEL
ExtProxy-1.0.3.dist-info/top_level.txt
ExtProxy-1.0.3.dist-info/zip-safe
ExtProxy-1.0.3.dist-info/RECORD
