Metadata-Version: 2.1
Name: ExtProxy
Version: 1.0.3
Summary: ExtProxy extend urllib2's ProxyHandler to support extra proxy types: HTTPS, SOCKS.
Home-page: https://github.com/SeaHOH/extproxy
Author: SeaHOH
Author-email: seahoh@gmail.com
License: MIT
Keywords: urllib ProxyHandler HTTPS SOCKS proxy
Platform: any
Classifier: Development Status :: 5 - Production/Stable
Classifier: License :: OSI Approved :: MIT License
Classifier: Operating System :: OS Independent
Classifier: Programming Language :: Python
Classifier: Programming Language :: Python :: 2
Classifier: Programming Language :: Python :: 3
Classifier: Topic :: Internet :: WWW/HTTP
Classifier: Topic :: Utilities
Requires-Python: >=2.7
License-File: LICENSE
